[
  {
    "id": "493f2d78-ebc4-42ea-83aa-ea556b4b733b",
    "type": "primary",
    "meta": "FREE",
    "headline": "Free custom clothes for any VRChat avatar",
    "body": "Open call for a clothing commission for any VRChat avatar, limited spots",
    "image": "",
    "progress": "0/10",
    "progressLabel": "Free Commissions",
    "showProgress": true,
    "showTermsLink": true,
    "links": [
      {
        "label": "CLICK ME!",
        "url": "https://paw-shop.github.io/paw.shop.docs/"
      }
    ],
    "accent": "#f7cade",
    "localized": {
      "en": {
        "meta": "FREE",
        "headline": "Free custom clothes for any VRChat avatar",
        "body": "Open call for a clothing commission for any VRChat avatar, limited spots",
        "progressLabel": "Free Commissions",
        "progress": "0/10",
        "showProgress": true,
        "showTermsLink": true,
        "links": [
          {
            "label": "CLICK ME!",
            "url": "https://paw-shop.github.io/paw.shop.docs/"
          }
        ]
      },
      "es": {
        "meta": "GRATIS",
        "headline": "Ropa personalizada gratis para cualquier avatar de VRChat",
        "body": "Convocatoria abierta para una comisión de ropa para cualquier avatar de VRChat, plazas limitadas",
        "progressLabel": "Comisiones gratuitas",
        "progress": "0/10",
        "showProgress": true,
        "showTermsLink": true,
        "links": [
          {
            "label": "Click Aquí!",
            "url": "https://paw-shop.github.io/paw.shop.docs/"
          }
        ]
      }
    }
  },
  {
    "id": "announcement-2",
    "type": "secondary",
    "meta": "ACTIVE COMMISSION SEARCH",
    "headline": "Portfolio growing",
    "body": "New pieces, versions, and galleries will keep being added as recent work comes in.",
    "image": "",
    "progress": "",
    "showProgress": false,
    "showTermsLink": false,
    "progressLabel": "Progress",
    "links": [],
    "accent": "#f7cade",
    "localized": {
      "es": {
        "meta": "BÚSQUEDA ACTIVA DE COMISIONES",
        "headline": "Portafolio en crecimiento",
        "body": "Se irán sumando nuevas piezas, versiones y galerías conforme salgan trabajos recientes.",
        "progressLabel": "Progreso",
        "progress": "",
        "showProgress": false,
        "showTermsLink": false,
        "links": []
      },
      "en": {
        "meta": "ACTIVE COMMISSION SEARCH",
        "headline": "Portfolio growing",
        "body": "New pieces, versions, and galleries will keep being added as recent work comes in.",
        "progressLabel": "Progress",
        "progress": "",
        "showProgress": false,
        "showTermsLink": false,
        "links": []
      }
    }
  }
]
